[
    {
        "desc": "Just before midnight June 22, an off-duty police officer radios that he is in a foot chase with a suspect through Monroe Place Apartments.",
        "id": 0,
        "step": 0,
        "title": "",
        "x": 77,
        "y": 50
    },
    {
        "desc": "Officer James Burns arrives minutes later. He disables his blue lights and siren. ",
        "id": 1,
        "step": 1,
        "title": "",
        "x": 9,
        "y": 12
    },
    {
        "desc": "Burns turns onto Monroe Place NE and slows his vehicle as he scans the area.",
        "id": 1,
        "step": 2,
        "title": "",
        "x": 46,
        "y": 19
    },
    {
        "desc": "Deravis Rogers, who is parked toward the end of the block, turns on his lights and drives north.",
        "id": 2,
        "step": 3,
        "title": "",
        "x": 41,
        "y": 64
    },
    {
        "desc": "Seeing the approaching vehicle, Burns angles his car towards the center of the road, chirps his siren and turns on his blue lights.",
        "id": 1,
        "step": 4,
        "title": "",
        "x": 45,
        "y": 26
    },
    {
        "desc": "The car continues north without stopping. Burns said he thought the driver was trying to escape. ",
        "id": 2,
        "step": 5,
        "title": "",
        "x": 48,
        "y": 41
    },
    {
        "desc": "As the car tries to drive around Burns' patrol vehicle, the officer jumps out and yells \"Stop!\" ",
        "id": 1,
        "step": 6,
        "title": "",
        "x": 44,
        "y": 30
    },
    {
        "desc": "Burns runs toward the rear of his vehicle. He fires one shot through Rogers' passenger side window, striking him in the head.",
        "id": 1,
        "step": 7,
        "title": "",
        "x": 43,
        "y": 25
    },
    {
        "desc": "Rogers' car coasts down Monroe Place, hops the curb of Monroe Drive, and crashes into a vehicle in a parking lot. Rogers is later pronounced dead.",
        "id": 2,
        "step": 8,
        "title": "",
        "x": 41,
        "y": 1
    }
]
